renovexpy/__init__.py
renovexpy/demo_streamlit.py
renovexpy/energyplus.py
renovexpy/geometry.py
renovexpy/geometry_new.py
renovexpy/heating_system.py
renovexpy/kpi.py
renovexpy/off_the_fly.py
renovexpy/optimization.py
renovexpy/parametric.py
renovexpy/pv.py
renovexpy/renovation.py
renovexpy/run_job.sh
renovexpy/schedules.py
renovexpy/sensitivity.py
renovexpy/surrogate.py
renovexpy/utils.py
renovexpy/data/A.idf
renovexpy/data/C1.idf
renovexpy/data/C2.idf
renovexpy/data/C4a.idf
renovexpy/data/D5c.idf
renovexpy/data/DHW_profiles.csv
renovexpy/data/DeBilt_2000.epw
renovexpy/data/DeBilt_2050.epw
renovexpy/data/DeBilt_2100.epw
renovexpy/data/NLD_DBL_EPW_NEN-18.epw
renovexpy/data/appliances_schedules.csv
renovexpy/data/energy_prices.csv
renovexpy/data/heatpump_capacity.csv
renovexpy/data/kostenkentallen.xlsx
renovexpy/data/materials.idf
renovexpy/data/net_metering.csv
renovexpy/data/ob_data.xlsx
renovexpy/data/occupancy_profiles.csv
renovexpy/data/pbl-2023-scenarios-voor-aardgas-en-elektriciteitsprijzen-voor-kleinverbruikers-in-de-periode-2025-2040_0.ods
renovexpy/data/schedules.idf
renovexpy/examples/demo.ipynb
renovexpy/examples/parametric.ipynb
renovexpy/examples/simulation.ipynb
renovexpy/old/random_sampling.py
renovexpy/old/surrogate.py
renovexpy/surrogate_models/Average CO2 exposure [ppm].joblib
renovexpy/surrogate_models/CO2 excess [h].joblib
renovexpy/surrogate_models/Electricity OPP [kW].joblib
renovexpy/surrogate_models/Electricity consumption [kWh].joblib
renovexpy/surrogate_models/Gas consumption [kWh].joblib
renovexpy/surrogate_models/Heating demand [kWh].joblib
renovexpy/surrogate_models/Operational cost [€].joblib
renovexpy/surrogate_models/Overheating [h].joblib
renovexpy-1.1.3.dist-info/METADATA
renovexpy-1.1.3.dist-info/WHEEL
renovexpy-1.1.3.dist-info/top_level.txt
renovexpy-1.1.3.dist-info/RECORD
