Metadata-Version: 2.4
Name: renovexpy
Version: 1.1.3
Summary: A Python toolbox for the Renovation Explorer project
Author-email: Alexis Cvetkov-Iliev <a.cvetkov.iliev@tue.nl>
Project-URL: Homepage, https://gitlab.tue.nl/bp-tue/renovatieverkenner/renovexpy
Classifier: Programming Language :: Python :: 3
Classifier: License :: OSI Approved :: MIT License
Classifier: Operating System :: OS Independent
Requires-Python: >=3.10
Requires-Dist: numpy
Requires-Dist: pandas
Requires-Dist: Geometry3D
Requires-Dist: shapely
Requires-Dist: tqdm
Requires-Dist: matplotlib
Requires-Dist: esoreader
Requires-Dist: scipy
Requires-Dist: numba
Requires-Dist: ipykernel
Requires-Dist: pythermalcomfort
Requires-Dist: pyarrow
Requires-Dist: joblib
Requires-Dist: trimesh[easy]
Requires-Dist: triangle
Requires-Dist: scikit-learn==1.5.2
Requires-Dist: fast-pareto
Requires-Dist: epw
Requires-Dist: openpyxl
Requires-Dist: streamlit
Requires-Dist: plotly
Requires-Dist: dash
